django_websockets/__init__.py
django_websockets/app.py
django_websockets/setup.py
django_websockets/teste.py
django_websockets/utils.py
django_websockets/consumers/__init__.py
django_websockets/groups/__init__.py
django_websockets/groups/backends/__init__.py
django_websockets/management/__init__.py
django_websockets/management/commands/__init__.py
django_websockets/management/commands/websockets_server.py
django_websockets/middlewares/__init__.py
django_websockets/middlewares/auth.py
django_websockets/middlewares/route.py
django_websockets/middlewares/scope.py
django_websockets/middlewares/utils.py
django_websockets/server/__init__.py
django_websockets/server/arguments.py
django_websockets/server/handler.py
django_websockets/server/horchestration.py
django_websockets/server/main.py
django_websockets/server/server.py
django_websockets/transport/__init__.py
django_websockets/transport/proto/__init__.py
django_websockets/transport/proto/wstransport_pb2.py
django_websockets/transport/proto/wstransport_pb2_grpc.py
django_websockets-0.0.10.dist-info/METADATA
django_websockets-0.0.10.dist-info/WHEEL
django_websockets-0.0.10.dist-info/top_level.txt
django_websockets-0.0.10.dist-info/RECORD
