Metadata-Version: 2.1
Name: django-websockets
Version: 0.0.10
Summary: This project is a case study of using Python Websockets as a websocket backend for Django.
Author-email: JRaylan <jeffersonraylan@gmail.com>
Project-URL: Homepage, https://github.com/jraylan/django_websockets
Project-URL: Bug Tracker, https://github.com/jraylan/django_websockets/issues
Classifier: Programming Language :: Python :: 3
Classifier: License :: OSI Approved :: MIT License
Classifier: Operating System :: Unix
Requires-Python: >=3.7
